MANIFEST.in
NEWS.txt
README.rst
py7file.py
setup.py
py7file.egg-info/PKG-INFO
py7file.egg-info/SOURCES.txt
py7file.egg-info/dependency_links.txt
py7file.egg-info/top_level.txt