Metadata-Version: 1.0
Name: py7file
Version: 0.7.4
Summary: Convenient File Handling Library
Home-page: http://github.com/titusz/py7file
Author: Titusz
Author-email: tp@py7.de
License: BSD
Keywords: file copy move backup unzip open os.path shutil wrapper api epub
Platform: UNKNOWN
Classifier: Development Status :: 4 - Beta
Classifier: Intended Audience :: Developers
Classifier: Intended Audience :: System Administrators
Classifier: License :: OSI Approved :: BSD License
Classifier: Operating System :: OS Independent
Classifier: Programming Language :: Python
Classifier: Programming Language :: Python :: 2.6
Classifier: Programming Language :: Python :: 2.7
Classifier: Topic :: Desktop Environment :: File Managers
Classifier: Topic :: System :: Filesystems
Classifier: Topic :: Software Development :: Libraries :: Python Modules
Classifier: Topic :: Utilities
